cryptochecker/__init__.py
cryptochecker/transaction.py
cryptochecker-0.0.5.dist-info/LICENSE
cryptochecker-0.0.5.dist-info/METADATA
cryptochecker-0.0.5.dist-info/WHEEL
cryptochecker-0.0.5.dist-info/top_level.txt
cryptochecker-0.0.5.dist-info/RECORD
