Metadata-Version: 2.1
Name: cryptochecker
Version: 0.0.5
Summary: Check any Bitcoin and Ethereum transaction
Home-page: https://github.com/Aegar6/cryptochecker
Author: Aegar6
Author-email: bogusz.krzyzanow@gmail.com
License: MIT
Keywords: crypto cryptocurrency cryptochecker bitcoin ethereum
Platform: UNKNOWN
Classifier: Programming Language :: Python :: 3
Requires-Python: >=3.6
Requires-Dist: requests
Requires-Dist: selectorlib
